dctl/__init__.py
dctl/commands/__init__.py
dctl/commands/env/__init__.py
dctl/commands/env/list.py
dctl/commands/env/set.py
dctl/commands/login.py
dctl/commands/logout.py
dctl/commands/logs.py
dctl/commands/new.py
dctl/commands/project/__init__.py
dctl/commands/project/list.py
dctl/commands/project/open.py
dctl/config.py
dctl/main.py
dctl/schemas/__init__.py
dctl/schemas/session.py
dctl/utils/__init__.py
dctl/utils/params.py
dctl/utils/session.py
dctl-0.0.18.dist-info/LICENSE
dctl-0.0.18.dist-info/METADATA
dctl-0.0.18.dist-info/WHEEL
dctl-0.0.18.dist-info/entry_points.txt
dctl-0.0.18.dist-info/RECORD
